atris/__init__.py
atris/admin.py
atris/apps.py
atris/middleware.py
atris/management/__init__.py
atris/management/commands/__init__.py
atris/management/commands/archive_old_historical_records.py
atris/management/commands/delete_old_historical_records.py
atris/management/commands/populate_initial_history.py
atris/migrations/0001_initial.py
atris/migrations/0002_historicalrecord_history_diff.py
atris/migrations/0003_added_indexes.py
atris/migrations/0004_archivedhistoricalrecord.py
atris/migrations/0005_auto_20160411_0250.py
atris/migrations/0006_auto_20160622_0720.py
atris/migrations/0007_related_field_history.py
atris/migrations/0008_object_id_text.py
atris/migrations/0009_auto_20190906_0509.py
atris/migrations/0010_alter_archivedhistoricalrecord_additional_data_and_more.py
atris/migrations/__init__.py
atris/models/__init__.py
atris/models/abstract_historical_record.py
atris/models/archived_historical_record.py
atris/models/exceptions.py
atris/models/helpers.py
atris/models/historical_record.py
atris/models/history_logging.py
django_atris-2.0.3.dist-info/LICENSE
django_atris-2.0.3.dist-info/METADATA
django_atris-2.0.3.dist-info/WHEEL
django_atris-2.0.3.dist-info/top_level.txt
django_atris-2.0.3.dist-info/RECORD
