Metadata-Version: 2.1
Name: django-atris
Version: 2.0.3
Summary: Django history logger that keeps track of changes on a global level.
Author-email: Bogdan Andrei Pop <bpop2232@gmail.com>
License: Copyright (c) [2023] [Bogdan Andrei Pop]
Project-URL: Homepage, https://github.com/pbs/django-atris
Keywords: django,database,history,logging
Classifier: License :: OSI Approved :: MIT License
Classifier: Programming Language :: Python :: 3
Requires-Python: >=3.8
License-File: LICENSE
Requires-Dist: Django <5,>=4
